setup.py
dsnd_probability_AB/Binomialdistribution.py
dsnd_probability_AB/Gaussiandistribution.py
dsnd_probability_AB/Generaldistribution.py
dsnd_probability_AB/__init__.py
dsnd_probability_AB.egg-info/PKG-INFO
dsnd_probability_AB.egg-info/SOURCES.txt
dsnd_probability_AB.egg-info/dependency_links.txt
dsnd_probability_AB.egg-info/not-zip-safe
dsnd_probability_AB.egg-info/top_level.txt