Metadata-Version: 1.0
Name: dsnd-probability-AB
Version: 1.1
Summary: Gaussian and Binomial distributions
Home-page: UNKNOWN
Author: Bloblo
Author-email: wrongemail@something.com
License: UNKNOWN
Platform: UNKNOWN
